reflex_altair/__init__.py
reflex_altair/component.py
reflex_altair/serializer.py
reflex_altair/type.py
reflex_altair-0.1.1.dist-info/METADATA
reflex_altair-0.1.1.dist-info/WHEEL
reflex_altair-0.1.1.dist-info/top_level.txt
reflex_altair-0.1.1.dist-info/RECORD
