Metadata-Version: 2.1
Name: reflex-altair
Version: 0.1.1
Summary: Reflex custom component to render altair/vega
Author-email: L�opold Grosjean <leo.grosjean@gmail.com>
License: Apache-2.0
Project-URL: homepage, https://github.com/LeoGrosjean/reflex-graphing/tree/main/altair
Project-URL: source, https://github.com/LeoGrosjean/reflex-graphing/tree/main/altair
Keywords: reflex,reflex-custom-components,altair,vega
Classifier: Development Status :: 4 - Beta
Requires-Python: >=3.9
Requires-Dist: reflex>=0.6.0
Provides-Extra: dev
Requires-Dist: build; extra == "dev"
Requires-Dist: twine; extra == "dev"
